[
  {
    "id": 1595907799304765445,
    "author_id": 1108431749820882947,
    "text": "If you watch any video today, make it this one. Andrew Tate absolutely nails the Covid scam in 90 seconds. \ud83d\udc47 https://t.co/gfWsKzg4Lq",
    "created_at": "11/24/2022 22:30:44",
    "retweet_count": 11499,
    "reply_count": 854,
    "like_count": 25520,
    "quote_count": 993,
    "lang": "en",
    "attachments": {
      "media_keys": [
        "7_1595907048457256961"
      ]
    }
  },
  {
    "id": 1596633572601106432,
    "author_id": 1593338559779713024,
    "text": "@LayahHeilpern The female Andrew Tate",
    "created_at": "11/26/2022 22:34:42",
    "retweet_count": 0,
    "reply_count": 0,
    "like_count": 0,
    "quote_count": 0,
    "lang": "en",
    "referenced_tweets": [
      {
        "id": 1596505855587135489,
        "type": "replied_to"
      }
    ]
  },
  {
    "id": 1596633547359805441,
    "author_id": 1596593204199055361,
    "text": "Andrew Tate shout out to ugly men!\n#AndrewTate #Motivation #shorts https://t.co/LHb8Yb4YYK",
    "created_at": "11/26/2022 22:34:36",
    "retweet_count": 0,
    "reply_count": 0,
    "like_count": 0,
    "quote_count": 0,
    "lang": "en",
    "attachments": {
      "media_keys": [
        "7_1596633450039083008"
      ]
    }
  },
  {
    "id": 1596633472298205185,
    "author_id": 1355689023692410882,
    "text": "@whosscookie @Cobratate Sorry to Chisholm your dreams, but that\u2019s not Andrew Tate. Also he is not a fan of u",
    "created_at": "11/26/2022 22:34:18",
    "retweet_count": 0,
    "reply_count": 0,
    "like_count": 0,
    "quote_count": 0,
    "lang": "en",
    "referenced_tweets": [
      {
        "id": 1596145908982624256,
        "type": "replied_to"
      }
    ]
  },
  {
    "id": 1596633457912066049,
    "author_id": 1421797437602160644,
    "text": "Calm down Andrew Tate. . https://t.co/qT8znRPR2Y",
    "created_at": "11/26/2022 22:34:15",
    "retweet_count": 0,
    "reply_count": 0,
    "like_count": 0,
    "quote_count": 0,
    "lang": "en",
    "referenced_tweets": [
      {
        "id": 1596630052539891712,
        "type": "quoted"
      }
    ]
  },
  {
    "id": 1596633399262937088,
    "author_id": 1276560512726323201,
    "text": "Before I knew about Andrew Tate, I was nothing. A loser even. One day my homie said, \"hey do you know the Top G\". I said no, so he turned on one of his podcasts. His words inspired me to turn my life around &amp; become an Alpha male. I now have 7 girlfriends &amp; a orange Bugatti. \ud83d\ude4f",
    "created_at": "11/26/2022 22:34:01",
    "retweet_count": 0,
    "reply_count": 0,
    "like_count": 0,
    "quote_count": 0,
    "lang": "en"
  },
  {
    "id": 1596633298465275904,
    "author_id": 1596593204199055361,
    "text": "Andrew Tate on how to be important man! (wait for the drop)\n#AndrewTate #Motivation #shorts https://t.co/cqhMXLohT4",
    "created_at": "11/26/2022 22:33:37",
    "retweet_count": 0,
    "reply_count": 0,
    "like_count": 0,
    "quote_count": 0,
    "lang": "en",
    "attachments": {
      "media_keys": [
        "7_1596633211718754307"
      ]
    }
  },
  {
    "id": 1596540569580613632,
    "author_id": 1477212786686148609,
    "text": "@Cobratate Before I knew about Andrew Tate, I was nothing. A loser even. One day my homie said, \"hey do you know the Top G\". I said no, so he turned on one of his podcasts. His words inspired me to turn my life around &amp; become an Alpha male. I now have 7 girlfriends &amp; a orange Bugatti. \ud83d\ude4f",
    "created_at": "11/26/2022 16:25:08",
    "retweet_count": 225,
    "reply_count": 392,
    "like_count": 5761,
    "quote_count": 34,
    "lang": "en",
    "referenced_tweets": [
      {
        "id": 1596540268744179712,
        "type": "replied_to"
      }
    ]
  },
  {
    "id": 1596633150230528000,
    "author_id": 1518680955124396032,
    "text": "@CassandraRules Dax (@thatsdax) or Andrew Tate would be interesting",
    "created_at": "11/26/2022 22:33:01",
    "retweet_count": 0,
    "reply_count": 0,
    "like_count": 0,
    "quote_count": 0,
    "lang": "en",
    "referenced_tweets": [
      {
        "id": 1596601599006228484,
        "type": "replied_to"
      }
    ]
  },
  {
    "id": 1596633134115819520,
    "author_id": 1593218732574253058,
    "text": "You can\u2019t win by yourself.\u00a0\n\u00a0\nAchieve status within an organization designed to combat the global oppression mechanism.\u00a0\n\u00a0\nThe rules are designed to crush, in the near future, you will need to live outside of ALL rules.\u00a0\n\u00a0\nFAILING to prepare, it's PREPARING to fail.\n\n-Andrew Tate https://t.co/6Ae9koL4kx",
    "created_at": "11/26/2022 22:32:57",
    "retweet_count": 0,
    "reply_count": 0,
    "like_count": 0,
    "quote_count": 0,
    "lang": "en",
    "attachments": {
      "media_keys": [
        "7_1596633056374390787"
      ]
    }
  },
  {
    "id": 1596632968667496449,
    "author_id": 1584299105781796874,
    "text": "Omg Andrew tate literally imagine Oh my god \ud83d\ude02\ud83d\ude02\ud83d\ude02\ud83d\ude02 preach my king Omg \ud83d\ude05\ud83d\ude2d\ud83d\ude2d\ud83d\ude2d\ud83d\ude2d IMAGINE!!!!! https://t.co/kGgZB0Bd2T",
    "created_at": "11/26/2022 22:32:18",
    "retweet_count": 0,
    "reply_count": 1,
    "like_count": 0,
    "quote_count": 0,
    "lang": "en",
    "referenced_tweets": [
      {
        "id": 1596522597813874689,
        "type": "quoted"
      }
    ]
  },
  {
    "id": 1596632917840728064,
    "author_id": 969210265928699904,
    "text": "@oshillex Brace yourself for the Andrew Tate fanboys",
    "created_at": "11/26/2022 22:32:06",
    "retweet_count": 0,
    "reply_count": 1,
    "like_count": 0,
    "quote_count": 0,
    "lang": "en",
    "referenced_tweets": [
      {
        "id": 1596630996031778817,
        "type": "replied_to"
      }
    ]
  },
  {
    "id": 1596539935275745280,
    "author_id": 615328000,
    "text": "I didn't know who Andrew Tate is till he was canceled or something so I went to research who he is... Turns out he has like five girlfriends and he's dated Lori Harvey before",
    "created_at": "11/26/2022 16:22:37",
    "retweet_count": 10,
    "reply_count": 4,
    "like_count": 81,
    "quote_count": 0,
    "lang": "en"
  },
  {
    "id": 1596632785745481728,
    "author_id": 1521294348062801920,
    "text": "I\u2019ve lived the life 99.9% of men wish they could live but aren't brave enough. \n \nBroke. \nRich. \nWorld champion fighter. \nChess genius. \n \nEtc. \n \nYou learn from experience. \n \nMy experiences &gt; 100 average men\u2019s lifetimes.\n\n- Andrew Tate",
    "created_at": "11/26/2022 22:31:34",
    "retweet_count": 0,
    "reply_count": 0,
    "like_count": 0,
    "quote_count": 0,
    "lang": "en"
  },
  {
    "id": 1596632772340506624,
    "author_id": 1037147213955256320,
    "text": "Fuck Twitter bitches. I like Andrew tate",
    "created_at": "11/26/2022 22:31:31",
    "retweet_count": 0,
    "reply_count": 1,
    "like_count": 0,
    "quote_count": 0,
    "lang": "en"
  },
  {
    "id": 1596583415603757057,
    "author_id": 1583350789904506882,
    "text": "andrew tate looks like johny sinns tho\ud83d\ude44\ud83e\udd14\ud83d\ude02",
    "created_at": "11/26/2022 19:15:24",
    "retweet_count": 8,
    "reply_count": 0,
    "like_count": 9,
    "quote_count": 0,
    "lang": "en"
  },
  {
    "id": 1594523807414640641,
    "author_id": 1386766191247695872,
    "text": "\u2b55\ufe0f Mic drop moment as Piers Morgan tries to excuse his support of medical tyranny, Andrew Tate is not impressed and exposes Morgan as the gatekeeping clown he truly is. https://t.co/OW3oZttroK",
    "created_at": "11/21/2022 02:51:15",
    "retweet_count": 64,
    "reply_count": 2,
    "like_count": 116,
    "quote_count": 1,
    "lang": "en",
    "attachments": {
      "media_keys": [
        "7_1594523768466145281"
      ]
    }
  },
  {
    "id": 1595857445620154368,
    "author_id": 1001414496819261440,
    "text": "Andrew Tate\u2019s Passport and Offshore Strategy https://t.co/ipMtMrsXBd via @YouTube",
    "created_at": "11/24/2022 19:10:39",
    "retweet_count": 7,
    "reply_count": 4,
    "like_count": 18,
    "quote_count": 0,
    "lang": "en"
  },
  {
    "id": 1596632517733392387,
    "author_id": 625403007,
    "text": "Andrew Tate would literally be nothing without the machinations of the Dread Council",
    "created_at": "11/26/2022 22:30:30",
    "retweet_count": 0,
    "reply_count": 0,
    "like_count": 0,
    "quote_count": 0,
    "lang": "en"
  },
  {
    "id": 1596632499022503937,
    "author_id": 1591205474312912896,
    "text": "Stop for 10 seconds.\n\nStop whatever you're doing, put your phone down. Clear your mind.\n\nDeep breath in and out.\n\nDo you notice how happy you feel?\n\nYou've been happy all of this time, but you weren\u2019t paying attention.\n\nKeep the smile.\n\nThen back to work. \n\n- Andrew Tate https://t.co/JzQ0swDbJQ",
    "created_at": "11/26/2022 22:30:26",
    "retweet_count": 0,
    "reply_count": 0,
    "like_count": 0,
    "quote_count": 0,
    "lang": "en",
    "attachments": {
      "media_keys": [
        "3_1596632494454906882"
      ]
    }
  },
  {
    "id": 1596632475446697984,
    "author_id": 1594099100600991746,
    "text": "\"I struggle with motivation\"\nOk then stay a loser\nGoodbye\n-Andrew Tate",
    "created_at": "11/26/2022 22:30:20",
    "retweet_count": 0,
    "reply_count": 0,
    "like_count": 0,
    "quote_count": 0,
    "lang": "en"
  },
  {
    "id": 1596632369376931840,
    "author_id": 1411408790159872007,
    "text": "@fartpenis4 @MichaelDelMario @SFCDR_Tal @livelaughyeett @iUsedToBeADuck You retweet anti Andrew Tate and still somehow you\u2019re bitchless, that\u2019s mad https://t.co/XqDU2Zzcmi",
    "created_at": "11/26/2022 22:29:55",
    "retweet_count": 0,
    "reply_count": 0,
    "like_count": 1,
    "quote_count": 0,
    "lang": "en",
    "referenced_tweets": [
      {
        "id": 1596615296135344128,
        "type": "replied_to"
      }
    ],
    "attachments": {
      "media_keys": [
        "3_1596632365031428096"
      ]
    }
  },
  {
    "id": 1596632339043401728,
    "author_id": 1594948826657587200,
    "text": "@John82449014 @jamesdo62602742 @jakeshieldsajj Always amazed at how late boomers find things. Have fun discovering Andrew Tate in 2025",
    "created_at": "11/26/2022 22:29:48",
    "retweet_count": 0,
    "reply_count": 0,
    "like_count": 0,
    "quote_count": 0,
    "lang": "en",
    "referenced_tweets": [
      {
        "id": 1596561525392621568,
        "type": "replied_to"
      }
    ]
  },
  {
    "id": 1596632300363595783,
    "author_id": 1593834577302282240,
    "text": "@MiloWear1A Andrew Tate",
    "created_at": "11/26/2022 22:29:39",
    "retweet_count": 0,
    "reply_count": 0,
    "like_count": 0,
    "quote_count": 0,
    "lang": "en",
    "referenced_tweets": [
      {
        "id": 1596473032561901568,
        "type": "replied_to"
      }
    ]
  },
  {
    "id": 1596292767122006016,
    "author_id": 1363904791236206603,
    "text": "Just a reminder that all those guys like Andrew Tate that are selling dudes a program to speak to women, really aren't. \n\nThey are just MLM schemes for guys to sell to other guys. https://t.co/DtqEErCox4",
    "created_at": "11/26/2022 00:00:28",
    "retweet_count": 928,
    "reply_count": 562,
    "like_count": 9028,
    "quote_count": 261,
    "lang": "en",
    "attachments": {
      "media_keys": [
        "3_1596292745986945024",
        "3_1596292753477902338",
        "3_1596292758116802561",
        "3_1596292762730524673"
      ]
    }
  },
  {
    "id": 1596632178372546560,
    "author_id": 1477352393775976451,
    "text": "@JonFibonacci @4rexFinn20 Like Kanye West and Andrew Tate who are worth billions more than you? Not saying I agree with them but it\u2019s certainly nothing to laugh at and a point to consider.",
    "created_at": "11/26/2022 22:29:09",
    "retweet_count": 0,
    "reply_count": 0,
    "like_count": 0,
    "quote_count": 0,
    "lang": "en",
    "referenced_tweets": [
      {
        "id": 1596596783458787329,
        "type": "replied_to"
      }
    ]
  },
  {
    "id": 1596632029080170498,
    "author_id": 1590201554463850496,
    "text": "When you\u2019re a rich powerful man who enjoys life and refuses to comply with society\u2019s norms -\n\nYou\u2019ll always be seen as an evil, bad person by the losers still stuck in the matrix. \n\nUnless you give them money.\n\n- Andrew Tate",
    "created_at": "11/26/2022 22:28:34",
    "retweet_count": 0,
    "reply_count": 0,
    "like_count": 0,
    "quote_count": 0,
    "lang": "en"
  },
  {
    "id": 1596619535225802752,
    "author_id": 1108431749820882947,
    "text": "I'm hardly an Andrew Tate fan. I hadn't heard of him until recently. And he's said some things I disagree with. But you know what? He's a fighter for freedom, a voice of common sense, and he's teaching young people to think for themselves, and be healthy. That is a great thing.",
    "created_at": "11/26/2022 21:38:55",
    "retweet_count": 10,
    "reply_count": 14,
    "like_count": 82,
    "quote_count": 0,
    "lang": "en"
  },
  {
    "id": 1596611947855609857,
    "author_id": 776272687,
    "text": "One year ago, I included Mikhaila as an example in my Kill to Party episode. She wanted an interview with me last December to clear her name regarding Andrew Tate, but also to cherrypick hot takes about comparing her to Casey Anthony (which I didn't).",
    "created_at": "11/26/2022 21:08:46",
    "retweet_count": 3,
    "reply_count": 2,
    "like_count": 53,
    "quote_count": 0,
    "lang": "en",
    "referenced_tweets": [
      {
        "id": 1596607631338053633,
        "type": "replied_to"
      }
    ]
  },
  {
    "id": 1596631785504329729,
    "author_id": 1586381252348837888,
    "text": "Quinn Tate Andrew Whyet #\u82cf\u5dde Abbott Beerbohm #\u9752\u5c9b Teresa Eve #\u5357\u901a Isabel Sidney https://t.co/4oVHjYosHR",
    "created_at": "11/26/2022 22:27:36",
    "retweet_count": 0,
    "reply_count": 0,
    "like_count": 0,
    "quote_count": 0,
    "lang": "en",
    "attachments": {
      "media_keys": [
        "7_1595744749910380546"
      ]
    }
  },
  {
    "id": 1596631783222624256,
    "author_id": 1532329835007205376,
    "text": "@VonTrippenhoff It\u2019s part of my cover\u2026I was trying to get a RT off Andrew Tate \u2026he\u2019s ignoring me so far ffs",
    "created_at": "11/26/2022 22:27:35",
    "retweet_count": 0,
    "reply_count": 1,
    "like_count": 0,
    "quote_count": 0,
    "lang": "en",
    "referenced_tweets": [
      {
        "id": 1596631272784564224,
        "type": "replied_to"
      }
    ]
  },
  {
    "id": 1596631774678892544,
    "author_id": 310672543,
    "text": "Andrew Tate is a gift https://t.co/QWVJyDpVsD",
    "created_at": "11/26/2022 22:27:33",
    "retweet_count": 0,
    "reply_count": 0,
    "like_count": 0,
    "quote_count": 0,
    "lang": "en",
    "referenced_tweets": [
      {
        "id": 1595907799304765445,
        "type": "quoted"
      }
    ]
  },
  {
    "id": 1596631692051374080,
    "author_id": 1452637226244861952,
    "text": "Andrew Tate Copypasta \u2013\u00a0Followchain https://t.co/qRClvhAB0y",
    "created_at": "11/26/2022 22:27:14",
    "retweet_count": 0,
    "reply_count": 0,
    "like_count": 0,
    "quote_count": 0,
    "lang": "en"
  },
  {
    "id": 1593333619291996162,
    "author_id": 1228645328313696257,
    "text": "Maybe I\u2019m not making it clear enough. THE ORGANIZATIONS AND INDIVIDUALS SUPPORTING AMBER HEARD ARE LEADING NAMES IN FEMINISM! \n\nAnd yall are worried about ANDREW TATE? What about Amber Heard, @DonnaHylton , @amyschumer , and other toxic women like @GloriaSteinem who SUPPORT THEM!",
    "created_at": "11/17/2022 20:01:52",
    "retweet_count": 19,
    "reply_count": 2,
    "like_count": 102,
    "quote_count": 1,
    "lang": "en",
    "referenced_tweets": [
      {
        "id": 1593333616482082817,
        "type": "replied_to"
      }
    ]
  },
  {
    "id": 1596631503479373824,
    "author_id": 1561603680205475840,
    "text": "i can\u2019t die i have to outlive andrew tate",
    "created_at": "11/26/2022 22:26:29",
    "retweet_count": 0,
    "reply_count": 0,
    "like_count": 1,
    "quote_count": 0,
    "lang": "en"
  },
  {
    "id": 1596631486920536064,
    "author_id": 1426607932527890434,
    "text": "@piersmorgan Andrew Tate owns you",
    "created_at": "11/26/2022 22:26:25",
    "retweet_count": 0,
    "reply_count": 0,
    "like_count": 0,
    "quote_count": 0,
    "lang": "en",
    "referenced_tweets": [
      {
        "id": 1596612473947201536,
        "type": "replied_to"
      }
    ]
  },
  {
    "id": 1596631191234699264,
    "author_id": 1354815618915033088,
    "text": "@ghostofcasa Bro why u pay money to put out your andrew tate looking advice",
    "created_at": "11/26/2022 22:25:14",
    "retweet_count": 0,
    "reply_count": 0,
    "like_count": 0,
    "quote_count": 0,
    "lang": "en",
    "referenced_tweets": [
      {
        "id": 1591783725414711296,
        "type": "replied_to"
      }
    ]
  },
  {
    "id": 1596540256350011393,
    "author_id": 1445000873726332941,
    "text": "Andrew Tate Snaps on Mask-Wearing, Slave-Minded Individuals Following the Media\u2019s Propaganda https://t.co/F2NSliTzHb",
    "created_at": "11/26/2022 16:23:54",
    "retweet_count": 25,
    "reply_count": 0,
    "like_count": 34,
    "quote_count": 2,
    "lang": "en",
    "attachments": {
      "media_keys": [
        "7_1596539867151958017"
      ]
    }
  },
  {
    "id": 1596259401169510401,
    "author_id": 1254787933493575684,
    "text": "Andrew Tate breaks down the absurdness of the Covid Narrative in 90 seconds.\n\n#MaskUp #MasksWork #maskmandate #mandates #NeverAgain \n\nhttps://t.co/lIZ363WAvg",
    "created_at": "11/25/2022 21:47:52",
    "retweet_count": 1,
    "reply_count": 0,
    "like_count": 6,
    "quote_count": 0,
    "lang": "en",
    "attachments": {
      "media_keys": [
        "7_1595907048457256961"
      ]
    }
  },
  {
    "id": 1596631097638469632,
    "author_id": 1430875089210388481,
    "text": "If you can't control your own mind then you are just a feather in the wind of life. \n\n-Andrew Tate",
    "created_at": "11/26/2022 22:24:52",
    "retweet_count": 0,
    "reply_count": 0,
    "like_count": 0,
    "quote_count": 0,
    "lang": "en"
  },
  {
    "id": 1596631032065069056,
    "author_id": 1439470346219008001,
    "text": "@sahil_marjara so go listen to some andrew tate",
    "created_at": "11/26/2022 22:24:36",
    "retweet_count": 0,
    "reply_count": 1,
    "like_count": 0,
    "quote_count": 0,
    "lang": "en",
    "referenced_tweets": [
      {
        "id": 1596435742347374593,
        "type": "replied_to"
      }
    ]
  },
  {
    "id": 1594147223989899265,
    "author_id": 1435266453108928515,
    "text": "Andrew Tate: To get women, you need to be rich and have the exact right mindset.\n\nJP: Attractive women will always be drawn to competent, powerful men\n\nPickup artists: You need present yourself like I do and take my $3000 course\n\nLiteral 10/10s with unemployed black drug dealers: https://t.co/oDDQjND7k6",
    "created_at": "11/20/2022 01:54:50",
    "retweet_count": 167,
    "reply_count": 11,
    "like_count": 620,
    "quote_count": 0,
    "lang": "en",
    "attachments": {
      "media_keys": [
        "7_1594147179853217792"
      ]
    }
  },
  {
    "id": 1596630975902978048,
    "author_id": 1592904722272370688,
    "text": "Stop for 10 seconds.\n\nStop whatever you're doing, put your phone down. Clear your mind.\n\nDeep breath in and out.\n\nGood.\n\nDo you notice how happy you feel?\n\nYou've been happy all of this time, but you weren\u2019t paying attention.\n\nKeep the smile.\n\nThen back to work. \n\n- Andrew Tate",
    "created_at": "11/26/2022 22:24:23",
    "retweet_count": 0,
    "reply_count": 0,
    "like_count": 0,
    "quote_count": 0,
    "lang": "en"
  },
  {
    "id": 1596630678174474245,
    "author_id": 1593343073110708228,
    "text": "Stop whatever you're doing, put your phone down. Clear your mind.\n\nDeep breath in and out.\n\nGood.\n\nDo you notice how happy you feel?\n\nYou've been happy all of this time, but you weren\u2019t paying attention.\n\nKeep the smile.\n\nThen back to work.\n\nLet's fucking go.\n\n- Andrew Tate",
    "created_at": "11/26/2022 22:23:12",
    "retweet_count": 0,
    "reply_count": 0,
    "like_count": 0,
    "quote_count": 0,
    "lang": "en"
  },
  {
    "id": 1596479940882464771,
    "author_id": 1190613715110027266,
    "text": "You hate Andrew Tate but you follow bob risky ?",
    "created_at": "11/26/2022 12:24:13",
    "retweet_count": 9,
    "reply_count": 4,
    "like_count": 60,
    "quote_count": 0,
    "lang": "en"
  },
  {
    "id": 1596630352415662091,
    "author_id": 1542196070133932032,
    "text": "@PstafarianPrice I need to work on some international venture that has me abroad for months at a time.\n\nOh God... It's Andrew Tate. That's the job.",
    "created_at": "11/26/2022 22:21:54",
    "retweet_count": 0,
    "reply_count": 0,
    "like_count": 1,
    "quote_count": 0,
    "lang": "en",
    "referenced_tweets": [
      {
        "id": 1596619520915169285,
        "type": "replied_to"
      }
    ]
  },
  {
    "id": 1596545629370605569,
    "author_id": 1500035129271406592,
    "text": "@Cobratate Before listening to Andrew Tate: \n\nBroke \nFat \n2 inches \n$200\nNo wife\n\nAfter listening to Andrew Tate: \n\n$30M networth \nSix pack \n7 inches \n4 Wives\n\nThank you Top G!",
    "created_at": "11/26/2022 16:45:15",
    "retweet_count": 19,
    "reply_count": 20,
    "like_count": 906,
    "quote_count": 1,
    "lang": "en",
    "referenced_tweets": [
      {
        "id": 1596540268744179712,
        "type": "replied_to"
      }
    ]
  },
  {
    "id": 1596630148396511233,
    "author_id": 479196023,
    "text": "If u glorify andrew tate you\u2019re a fuckin cornball",
    "created_at": "11/26/2022 22:21:05",
    "retweet_count": 0,
    "reply_count": 0,
    "like_count": 1,
    "quote_count": 0,
    "lang": "en"
  },
  {
    "id": 1596630092351946752,
    "author_id": 1591063113452949505,
    "text": "You\u2019re influenced by your environment whether you accept it or not.\n\nTolerate weakness? \n\nYou will be weak.\n\nOnly allow strength and ambition?\n\nYour life will reflect it.\n\n- Andrew Tate",
    "created_at": "11/26/2022 22:20:52",
    "retweet_count": 0,
    "reply_count": 0,
    "like_count": 0,
    "quote_count": 0,
    "lang": "en"
  },
  {
    "id": 1596630084068478976,
    "author_id": 1180084096908824580,
    "text": "Andrew tate doing God's work\ud83d\ude4c",
    "created_at": "11/26/2022 22:20:50",
    "retweet_count": 0,
    "reply_count": 0,
    "like_count": 0,
    "quote_count": 0,
    "lang": "en"
  },
  {
    "id": 1596629904644530176,
    "author_id": 1593008883043385344,
    "text": "Andrew Tate: Why i respect Islam?\n\n#FIFAWorldCup https://t.co/YRkjAGfSWe",
    "created_at": "11/26/2022 22:20:07",
    "retweet_count": 0,
    "reply_count": 0,
    "like_count": 0,
    "quote_count": 0,
    "lang": "en",
    "attachments": {
      "media_keys": [
        "7_1596629028131176448"
      ]
    }
  },
  {
    "id": 1596629824046616577,
    "author_id": 1104764651219251200,
    "text": "@thatotherharry I have a question...\n\nWho the fuck is Andrew Tate?",
    "created_at": "11/26/2022 22:19:48",
    "retweet_count": 0,
    "reply_count": 1,
    "like_count": 0,
    "quote_count": 0,
    "lang": "en",
    "referenced_tweets": [
      {
        "id": 1596625672927338496,
        "type": "replied_to"
      }
    ]
  },
  {
    "id": 1596628801399975936,
    "author_id": 1365086052256538628,
    "text": "found Andrew Tate at the park https://t.co/scklRyKXd0",
    "created_at": "11/26/2022 22:15:44",
    "retweet_count": 3,
    "reply_count": 0,
    "like_count": 4,
    "quote_count": 0,
    "lang": "en",
    "attachments": {
      "media_keys": [
        "7_1596628716104425472"
      ]
    }
  },
  {
    "id": 1596629584044515328,
    "author_id": 1594099100600991746,
    "text": "I would be mad at this but, Andrew Tate tought me that females and LGBT dont care, so leave them #sigmasonly https://t.co/jucpvFvo7z",
    "created_at": "11/26/2022 22:18:51",
    "retweet_count": 0,
    "reply_count": 0,
    "like_count": 0,
    "quote_count": 0,
    "lang": "en",
    "attachments": {
      "media_keys": [
        "3_1596629580500066306"
      ]
    }
  },
  {
    "id": 1596485648130592769,
    "author_id": 1392501840248401926,
    "text": "@Cobratate I have no girlfriend, friends, family or any hobbies I have officially decided to dedicate my life to defending Andrew Tate. My one and only goal is to make sure everyone calls him the Top G. I don't care about my personal life anymore as long as Andrew Tate is known as the Top G",
    "created_at": "11/26/2022 12:46:54",
    "retweet_count": 16,
    "reply_count": 40,
    "like_count": 549,
    "quote_count": 3,
    "lang": "en",
    "referenced_tweets": [
      {
        "id": 1596484186655043584,
        "type": "replied_to"
      }
    ]
  },
  {
    "id": 1596629181747855362,
    "author_id": 1593200698124025857,
    "text": "Andrew \"I really don't know what Kylie Jenner looks like\" Tate",
    "created_at": "11/26/2022 22:17:15",
    "retweet_count": 0,
    "reply_count": 0,
    "like_count": 0,
    "quote_count": 0,
    "lang": "en"
  },
  {
    "id": 1596628879262642177,
    "author_id": 1591384609408765953,
    "text": "@Morpheusresist thank you. \n\nyour words opened the door to my enlightenment Andrew Tate.",
    "created_at": "11/26/2022 22:16:03",
    "retweet_count": 0,
    "reply_count": 0,
    "like_count": 0,
    "quote_count": 0,
    "lang": "en",
    "referenced_tweets": [
      {
        "id": 1596532886211264512,
        "type": "replied_to"
      }
    ]
  },
  {
    "id": 1596628816801169408,
    "author_id": 1536233730905362434,
    "text": "@LeeGreenOne Also if he has both british and american accent does he sound like andrew tate",
    "created_at": "11/26/2022 22:15:48",
    "retweet_count": 0,
    "reply_count": 1,
    "like_count": 1,
    "quote_count": 0,
    "lang": "en",
    "referenced_tweets": [
      {
        "id": 1596628624966553600,
        "type": "replied_to"
      }
    ]
  },
  {
    "id": 1596628706281558016,
    "author_id": 1056944327614754817,
    "text": "Alot of Andrew Tate fans never watched Johnny Bravo and it shows.",
    "created_at": "11/26/2022 22:15:22",
    "retweet_count": 0,
    "reply_count": 0,
    "like_count": 0,
    "quote_count": 0,
    "lang": "en"
  },
  {
    "id": 1596628627856461824,
    "author_id": 1311925727193751553,
    "text": "\"If you tolerate to everything then you stand for nothing.\" -Andrew Tate https://t.co/0JFvyNTZkN",
    "created_at": "11/26/2022 22:15:03",
    "retweet_count": 0,
    "reply_count": 0,
    "like_count": 0,
    "quote_count": 0,
    "lang": "en",
    "referenced_tweets": [
      {
        "id": 1596356169752539136,
        "type": "quoted"
      }
    ]
  },
  {
    "id": 1596628606704553984,
    "author_id": 1254214726327906304,
    "text": "@Eze102010 @A_blackflame @UjuAnya Because emotions are feminine, if women are hated femininity in men will absolutely be hated. Misandrists dont hate emotional men, misogynists do, i.e. andrew tate thinking crying and being nice is for pussies. I absolutely agree though black ppl should travel more.",
    "created_at": "11/26/2022 22:14:58",
    "retweet_count": 0,
    "reply_count": 1,
    "like_count": 0,
    "quote_count": 0,
    "lang": "en",
    "referenced_tweets": [
      {
        "id": 1596627957048520705,
        "type": "replied_to"
      }
    ]
  },
  {
    "id": 1596628490857877504,
    "author_id": 1594549630058090498,
    "text": "@Cobratate Well, good thing I started following andrew tate 1 whole year ago\ud83e\udd18",
    "created_at": "11/26/2022 22:14:30",
    "retweet_count": 0,
    "reply_count": 0,
    "like_count": 0,
    "quote_count": 0,
    "lang": "en",
    "referenced_tweets": [
      {
        "id": 1596522597813874689,
        "type": "replied_to"
      }
    ]
  },
  {
    "id": 1596628400692932609,
    "author_id": 1589969756362260480,
    "text": "Stop for 10 seconds.\n\nDeep breath in and out.\n\nGood.\n\nDo you notice how happy you feel?\n\nYou've been happy all of this time, but you weren\u2019t paying attention.\n\nKeep the smile.\n\nThen back to work. \n\nLet's fucking go.\n\n- Andrew Tate",
    "created_at": "11/26/2022 22:14:09",
    "retweet_count": 0,
    "reply_count": 0,
    "like_count": 0,
    "quote_count": 0,
    "lang": "en"
  },
  {
    "id": 1596628225869742080,
    "author_id": 1588887935822209024,
    "text": "Andrew Tate on how you have been LIED TO about what happiness is and what being happy actually means. https://t.co/yfEg9ozJtS",
    "created_at": "11/26/2022 22:13:27",
    "retweet_count": 0,
    "reply_count": 0,
    "like_count": 0,
    "quote_count": 0,
    "lang": "en",
    "attachments": {
      "media_keys": [
        "7_1596628050095087616"
      ]
    }
  },
  {
    "id": 1596628067824599040,
    "author_id": 1392493405444395011,
    "text": "Why does @FnMoneymaker think he is Andrew tate \ud83d\ude02 https://t.co/c6WLfxOWtU",
    "created_at": "11/26/2022 22:12:49",
    "retweet_count": 0,
    "reply_count": 12,
    "like_count": 49,
    "quote_count": 0,
    "lang": "en",
    "attachments": {
      "media_keys": [
        "3_1596628061713211392"
      ]
    }
  },
  {
    "id": 1596628052166967297,
    "author_id": 793756243596673024,
    "text": "I didn't knew much about this Andrew Tate guy but this reads like a top-tier parody account, and yet it's not a joke. https://t.co/QQvT4TZNiM",
    "created_at": "11/26/2022 22:12:46",
    "retweet_count": 0,
    "reply_count": 0,
    "like_count": 0,
    "quote_count": 0,
    "lang": "en",
    "referenced_tweets": [
      {
        "id": 1596522597813874689,
        "type": "quoted"
      }
    ]
  },
  {
    "id": 1596627981270913024,
    "author_id": 1290131888435154945,
    "text": "i think Andrew Tate could g check Batman what y\u2019all think",
    "created_at": "11/26/2022 22:12:29",
    "retweet_count": 0,
    "reply_count": 0,
    "like_count": 1,
    "quote_count": 0,
    "lang": "en"
  },
  {
    "id": 1596313343681249280,
    "author_id": 4850036245,
    "text": "Andrew Tate Is A DEVIL WORSHIPPER Named Anton LaVey That Created The Church Of SATAN! https://t.co/bkCkPdTFjN",
    "created_at": "11/26/2022 01:22:13",
    "retweet_count": 1,
    "reply_count": 0,
    "like_count": 1,
    "quote_count": 1,
    "lang": "en"
  },
  {
    "id": 1596598588947435520,
    "author_id": 1588501579132719104,
    "text": "@Cobratate I have no girlfriend, friends or any hobbies I have officially decided to dedicate my life to defending Andrew tate. My one and only goal is to make sure everyone calls him the top g. I don\u2019t care about my personal life anymore as long as Tate is known as the top g",
    "created_at": "11/26/2022 20:15:41",
    "retweet_count": 6,
    "reply_count": 10,
    "like_count": 73,
    "quote_count": 0,
    "lang": "en",
    "referenced_tweets": [
      {
        "id": 1596598289717071872,
        "type": "replied_to"
      }
    ]
  },
  {
    "id": 1596627509176832000,
    "author_id": 1386579606111612938,
    "text": "Guy on the stephen colbert tv show band who looks like Andrew tate? @cobratate ? https://t.co/IIa5ukOsPX",
    "created_at": "11/26/2022 22:10:36",
    "retweet_count": 0,
    "reply_count": 0,
    "like_count": 0,
    "quote_count": 0,
    "lang": "en",
    "attachments": {
      "media_keys": [
        "3_1596627281216430080"
      ]
    }
  },
  {
    "id": 1596180539546906624,
    "author_id": 1578404771739860993,
    "text": "hii im not new to twt but just made this acc i stan one direction (ot5 and solo), 5sos, joshua bassett, sabrina carpenter, obx, sturniolo triplets, tate mcrae, jenna ortega, dylan o'brien, marvel, tom holland, zendaya, andrew garfield, gilmore girls ! rt to help me find moots pls",
    "created_at": "11/25/2022 16:34:30",
    "retweet_count": 1,
    "reply_count": 0,
    "like_count": 3,
    "quote_count": 0,
    "lang": "en"
  },
  {
    "id": 1596601822801600512,
    "author_id": 930577538484551681,
    "text": "@CassandraRules Andrew Tate",
    "created_at": "11/26/2022 20:28:32",
    "retweet_count": 2,
    "reply_count": 2,
    "like_count": 150,
    "quote_count": 0,
    "lang": "en",
    "referenced_tweets": [
      {
        "id": 1596601599006228484,
        "type": "replied_to"
      }
    ]
  },
  {
    "id": 1593073745861963777,
    "author_id": 1539396470922792961,
    "text": "Andrew Tate on the clown world. https://t.co/iwaFfhDp5M",
    "created_at": "11/17/2022 02:49:13",
    "retweet_count": 1669,
    "reply_count": 127,
    "like_count": 14757,
    "quote_count": 75,
    "lang": "en",
    "attachments": {
      "media_keys": [
        "7_1593072676742041602"
      ]
    }
  },
  {
    "id": 1595890485121454080,
    "author_id": 1173755797052022784,
    "text": "@Cobratate When I wake up, I say good morning to all 53 posters of Andrew Tate in my room. I then get out of bed and change into my Andrew Tate merch. After that I go to work, thinking about Andrew Tate and how he is the TOP G. When I get home, I get under my Andrew Tate blanket and sleep.",
    "created_at": "11/24/2022 21:21:56",
    "retweet_count": 205,
    "reply_count": 163,
    "like_count": 4423,
    "quote_count": 19,
    "lang": "en",
    "referenced_tweets": [
      {
        "id": 1595890423062462467,
        "type": "replied_to"
      }
    ]
  },
  {
    "id": 1596484831499747329,
    "author_id": 1566638319987032065,
    "text": "The average person = win win lose \n \nElites = win win win lose\n \nThat extra win is hugely important. \n \nIt makes sure 99% of earth can never catch you - no matter how hard they work. \n \nWHERE does the extra win come from? \n \nTheir network.\n\n- Andrew Tate",
    "created_at": "11/26/2022 12:43:39",
    "retweet_count": 2,
    "reply_count": 3,
    "like_count": 29,
    "quote_count": 0,
    "lang": "en"
  },
  {
    "id": 1596627159099088897,
    "author_id": 851179310459367429,
    "text": "@ZubyMusic Jordan Peterson\nAndrew tate",
    "created_at": "11/26/2022 22:09:13",
    "retweet_count": 0,
    "reply_count": 0,
    "like_count": 0,
    "quote_count": 0,
    "lang": "en",
    "referenced_tweets": [
      {
        "id": 1595123315311419393,
        "type": "replied_to"
      }
    ]
  },
  {
    "id": 1596627066014736385,
    "author_id": 1550762353020379136,
    "text": "@DarrenJBeattie Nick Fuentes, Alex Jones, David Icke, Donald Trump, Andrew Tate",
    "created_at": "11/26/2022 22:08:51",
    "retweet_count": 0,
    "reply_count": 0,
    "like_count": 0,
    "quote_count": 0,
    "lang": "en",
    "referenced_tweets": [
      {
        "id": 1595942243612774400,
        "type": "replied_to"
      }
    ]
  },
  {
    "id": 1596511075830493185,
    "author_id": 1420919062285201408,
    "text": "ANDREW TATE @Cobratate \nLost\n60 MILLION ON CRYPTO IN 2022 \n\nHIS BANKS ACCOUNTS WERE SHUT DOWN \nHE HAD LESS THAN 10 MILLION TO HIS NAME\nAUGUST 2022\n\nHE WAS OFFERED 100 MILLION  TO CONVERT TO ISLAM \u262a\ufe0f  BY RICH BILLIONAIRES \nAS A WAY TO SPREAD ISLAM TO THE YOUTH\nWHO TATE INFLUENCES",
    "created_at": "11/26/2022 14:27:56",
    "retweet_count": 15,
    "reply_count": 20,
    "like_count": 169,
    "quote_count": 5,
    "lang": "en"
  },
  {
    "id": 1596626673554042881,
    "author_id": 858715255198928896,
    "text": "@ilikecolorado @Cobratate be honest, would u let Andrew tate tap?",
    "created_at": "11/26/2022 22:07:17",
    "retweet_count": 0,
    "reply_count": 0,
    "like_count": 1,
    "quote_count": 0,
    "lang": "en",
    "referenced_tweets": [
      {
        "id": 1596531694282059777,
        "type": "replied_to"
      }
    ]
  },
  {
    "id": 1596626591563411456,
    "author_id": 1204322727492046848,
    "text": "@cowboylikerita is that andrew tate\u2019s secret account? cuz wtf",
    "created_at": "11/26/2022 22:06:57",
    "retweet_count": 0,
    "reply_count": 1,
    "like_count": 1,
    "quote_count": 0,
    "lang": "en",
    "referenced_tweets": [
      {
        "id": 1596625805907759104,
        "type": "replied_to"
      }
    ]
  },
  {
    "id": 1596626395118985216,
    "author_id": 1586112564328648705,
    "text": "@Cobratate One day a friend of mine said, there is a guy who appears Top Les on YouTube, uses a lot N words, and says to those who are complaining about his orange \ud83c\udf4a Bugatti, what colour is your Bugatti?, It seemed wired to me, but now I'm a fan of Andrew Tate.",
    "created_at": "11/26/2022 22:06:11",
    "retweet_count": 0,
    "reply_count": 0,
    "like_count": 0,
    "quote_count": 0,
    "lang": "en",
    "referenced_tweets": [
      {
        "id": 1596540268744179712,
        "type": "replied_to"
      }
    ]
  },
  {
    "id": 1596626349401444352,
    "author_id": 1589421309221543936,
    "text": "The people I don't want following me are sexist, racist, homophobic andThose white power people (like bffr)\nAnd if you follow the real Andrew Tate fuck off\n(By the way if you want to text BECAUSE I HAVE TO SAY THIS AGAIN don't be weird and I don't care if you're horny)",
    "created_at": "11/26/2022 22:06:00",
    "retweet_count": 0,
    "reply_count": 1,
    "like_count": 4,
    "quote_count": 0,
    "lang": "en"
  },
  {
    "id": 1593998742956707841,
    "author_id": 1325770397996867586,
    "text": "Andrew Tate is what incels think is a ladies man\nAnd Elon Musk is what incels think is a smart man.\n\nKeep that in mind",
    "created_at": "11/19/2022 16:04:50",
    "retweet_count": 116,
    "reply_count": 74,
    "like_count": 850,
    "quote_count": 6,
    "lang": "en"
  },
  {
    "id": 1596626153330323456,
    "author_id": 1595165557061521422,
    "text": "Stop for 10 seconds.\n\nStop whatever you're doing, put your phone down. Clear your mind. Breath.\n\nGood.\n\nDo you notice how happy you feel?\n\nYou've been happy all of this time, but you weren\u2019t paying attention.\n\nKeep the smile.\n\nThen back to work. \n\nLet's fucking go.\n\n- Andrew Tate",
    "created_at": "11/26/2022 22:05:13",
    "retweet_count": 0,
    "reply_count": 0,
    "like_count": 0,
    "quote_count": 0,
    "lang": "en"
  },
  {
    "id": 1596626099462471681,
    "author_id": 735587667186978817,
    "text": "@vjeannek @DoodlesTrks @ski_nh @JustDrew8055 @GordoCDA Oh lord he gone Romanian AOC Andrew Tate (14yrs)  .. \ud83d\ude33 https://t.co/ZrYbj7qC4Z",
    "created_at": "11/26/2022 22:05:00",
    "retweet_count": 0,
    "reply_count": 0,
    "like_count": 0,
    "quote_count": 0,
    "lang": "en",
    "referenced_tweets": [
      {
        "id": 1596625063385903104,
        "type": "replied_to"
      }
    ],
    "attachments": {
      "media_keys": [
        "16_1596626091191390208"
      ]
    }
  },
  {
    "id": 1596625968550092801,
    "author_id": 1506638490083147777,
    "text": "@Cobratate Imagine you watch Andrew Tate everyday to fill your gap of masculine men since we\u2019re lacking it in society",
    "created_at": "11/26/2022 22:04:29",
    "retweet_count": 0,
    "reply_count": 0,
    "like_count": 0,
    "quote_count": 0,
    "lang": "en",
    "referenced_tweets": [
      {
        "id": 1596467456998281216,
        "type": "replied_to"
      }
    ]
  },
  {
    "id": 1596625931103535104,
    "author_id": 224957584,
    "text": "@AmanahQ_ @BornAKang Calm down Andrew tate",
    "created_at": "11/26/2022 22:04:20",
    "retweet_count": 0,
    "reply_count": 0,
    "like_count": 0,
    "quote_count": 0,
    "lang": "en",
    "referenced_tweets": [
      {
        "id": 1596623762547351553,
        "type": "replied_to"
      }
    ]
  },
  {
    "id": 1596625716300419072,
    "author_id": 68486989,
    "text": "@NoLeftyEsty @DuckDuckGoUX @elonmusk It absolutely does. I tried to search for something about Andrew Tate and the only thing you find is hate. Just like Google. It\u2019s infuriating. @elonmusk could start a search engine in his free time\ud83d\ude02! I know he has none lately but geez!",
    "created_at": "11/26/2022 22:03:29",
    "retweet_count": 0,
    "reply_count": 0,
    "like_count": 0,
    "quote_count": 0,
    "lang": "en",
    "referenced_tweets": [
      {
        "id": 1596566184161312769,
        "type": "replied_to"
      }
    ]
  },
  {
    "id": 1596625712361897984,
    "author_id": 1549782892405981189,
    "text": "\u201cThe hallmark of a real man is controlling himself, controlling his emotions, and acting appropriately regardless of how he feels.\u201d \n-Emory Andrew Tate III aka TopG",
    "created_at": "11/26/2022 22:03:28",
    "retweet_count": 0,
    "reply_count": 0,
    "like_count": 0,
    "quote_count": 0,
    "lang": "en"
  },
  {
    "id": 1596625672927338496,
    "author_id": 916333489041104897,
    "text": "why the fuck is Andrew Tate back",
    "created_at": "11/26/2022 22:03:18",
    "retweet_count": 0,
    "reply_count": 1,
    "like_count": 3,
    "quote_count": 0,
    "lang": "en"
  },
  {
    "id": 1596625657135763456,
    "author_id": 1595165557061521422,
    "text": "Andrew Tate on why men live harder lives \ud83d\udcaa https://t.co/ncSFcLsaLj",
    "created_at": "11/26/2022 22:03:15",
    "retweet_count": 0,
    "reply_count": 0,
    "like_count": 0,
    "quote_count": 0,
    "lang": "en",
    "attachments": {
      "media_keys": [
        "7_1596625563082448902"
      ]
    }
  },
  {
    "id": 1596625438771712000,
    "author_id": 1575616475603288066,
    "text": "MAKE HER REGRET! Andrew Tate On Relationships! Relationship Advice For\u00a0Men! https://t.co/x1VRC7jZvW https://t.co/npqRtHLEcZ",
    "created_at": "11/26/2022 22:02:23",
    "retweet_count": 0,
    "reply_count": 0,
    "like_count": 0,
    "quote_count": 0,
    "lang": "en"
  },
  {
    "id": 1596625398271737856,
    "author_id": 3057842899,
    "text": "Based Andrew Tate https://t.co/nydgSvLgF7",
    "created_at": "11/26/2022 22:02:13",
    "retweet_count": 0,
    "reply_count": 0,
    "like_count": 0,
    "quote_count": 0,
    "lang": "en",
    "referenced_tweets": [
      {
        "id": 1596522597813874689,
        "type": "quoted"
      }
    ]
  },
  {
    "id": 1596625260715311104,
    "author_id": 919282003459022848,
    "text": "@zez1ty @stdustfustfu u tryna meet andrew tate",
    "created_at": "11/26/2022 22:01:40",
    "retweet_count": 0,
    "reply_count": 0,
    "like_count": 1,
    "quote_count": 0,
    "lang": "en",
    "referenced_tweets": [
      {
        "id": 1596616753748267010,
        "type": "replied_to"
      }
    ]
  },
  {
    "id": 1596625191190245377,
    "author_id": 1562495782292320256,
    "text": "Andrew Tate has been banned from Belgium https://t.co/pDVZuzUgdJ",
    "created_at": "11/26/2022 22:01:24",
    "retweet_count": 0,
    "reply_count": 0,
    "like_count": 0,
    "quote_count": 0,
    "lang": "en",
    "attachments": {
      "media_keys": [
        "3_1596625189244063744",
        "3_1596625189252390912"
      ]
    }
  },
  {
    "id": 1596624868350791680,
    "author_id": 1430948686771728384,
    "text": "Will the illuminati take out Kanye first or Andrew Tate? It will depend on who's got the best Security details https://t.co/ApZPSLn2Nv",
    "created_at": "11/26/2022 22:00:07",
    "retweet_count": 1,
    "reply_count": 1,
    "like_count": 4,
    "quote_count": 0,
    "lang": "en",
    "attachments": {
      "media_keys": [
        "7_1596624817788166145"
      ]
    }
  },
  {
    "id": 1596624853498761217,
    "author_id": 1506123277097480201,
    "text": "@KeypicksMMA @TEAMMCGOAT Andrew Tate",
    "created_at": "11/26/2022 22:00:03",
    "retweet_count": 0,
    "reply_count": 0,
    "like_count": 1,
    "quote_count": 0,
    "lang": "en",
    "referenced_tweets": [
      {
        "id": 1596617196532375554,
        "type": "replied_to"
      }
    ]
  },
  {
    "id": 1596624820057563137,
    "author_id": 130924781,
    "text": "I'm not one to agree with Andrew Tate (usually ever), but he hits a home run regarding the covid nonsense:\nhttps://t.co/u82zCwz9D6",
    "created_at": "11/26/2022 21:59:55",
    "retweet_count": 0,
    "reply_count": 0,
    "like_count": 0,
    "quote_count": 0,
    "lang": "en"
  },
  {
    "id": 1596624802823000064,
    "author_id": 1506123277097480201,
    "text": "@TEAMMCGOAT McGregor and Andrew Tate for sure",
    "created_at": "11/26/2022 21:59:51",
    "retweet_count": 0,
    "reply_count": 0,
    "like_count": 1,
    "quote_count": 0,
    "lang": "en",
    "referenced_tweets": [
      {
        "id": 1596610671994900480,
        "type": "replied_to"
      }
    ]
  },
  {
    "id": 1596624716982550533,
    "author_id": 1495391576805330944,
    "text": "@Itzz_CryptoPaul @TERRAformearth1 @spacetime345 @NewOrthophony @TheWestHamVault @Christheking777 @Hotdoge27 @Paradoxmeta_io sound like an andrew tate follower lmao",
    "created_at": "11/26/2022 21:59:31",
    "retweet_count": 0,
    "reply_count": 0,
    "like_count": 0,
    "quote_count": 0,
    "lang": "en",
    "referenced_tweets": [
      {
        "id": 1596191559095316481,
        "type": "replied_to"
      }
    ]
  }
]